tl_code/__init__.py
tl_code/exp.py
tl_code-0.3.dist-info/METADATA
tl_code-0.3.dist-info/WHEEL
tl_code-0.3.dist-info/top_level.txt
tl_code-0.3.dist-info/RECORD
