Metadata-Version: 2.4
Name: tl_code
Version: 0.3
Summary: A TL package
Author: NaveenTheGreat
Classifier: Programming Language :: Python :: 3
Classifier: License :: OSI Approved :: MIT License
Classifier: Operating System :: OS Independent
Requires-Python: >=3.6
Dynamic: author
Dynamic: classifier
Dynamic: description-content-type
Dynamic: requires-python
Dynamic: summary
